fair_mobility_models/__init__.py
fair_mobility_models/fairmobil.py
fair_mobility_models/gravity.py
fair_mobility_models/radiation.py
fair_mobility_models-0.0.1.dist-info/METADATA
fair_mobility_models-0.0.1.dist-info/WHEEL
fair_mobility_models-0.0.1.dist-info/entry_points.txt
fair_mobility_models-0.0.1.dist-info/RECORD
