Metadata-Version: 2.3
Name: fair_mobility_models
Version: 0.0.1
Summary: An extension of the fair-mobil package
Author-email: The Puffins <jackmc@uw.edu>
License-Expression: MIT
Classifier: Development Status :: 3 - Alpha
Classifier: Intended Audience :: Developers
Classifier: License :: OSI Approved :: MIT License
Classifier: Operating System :: OS Independent
Classifier: Programming Language :: Python
Classifier: Programming Language :: Python :: 3
Classifier: Programming Language :: Python :: 3.8
Classifier: Programming Language :: Python :: 3.9
Requires-Python: >=3.8
Requires-Dist: geopandas>=0.9.0
Requires-Dist: numpy>=1.20.0
Requires-Dist: pandas>=1.2.0
Requires-Dist: plotly>=5.0.0
Requires-Dist: scikit-mobility>=1.3.1
Requires-Dist: scipy>=1.6.0
